{
	"cursor": "/Users/latona2/bitbucket/sap-api-integrations-sales-inquiry-reads/SAP_API_Caller/caller.go#L160",
	"function": "sap-api-integrations-sales-inquiry-reads/SAP_API_Caller.(*SAPAPICaller).Item",
	"level": "INFO",
	"message": [
		{
			"SalesInquiry": "10000000",
			"SalesInquiryItem": "10",
			"PricingProcedureStep": "11",
			"PricingProcedureCounter": "1",
			"ConditionApplication": "V",
			"ConditionType": "PR00",
			"PricingDateTime": "1998-02-01",
			"ConditionCalculationType": "C",
			"ConditionBaseValue": "15.000000000",
			"ConditionRateValue": "1000.000000000",
			"ConditionCurrency": "EUR",
			"ConditionQuantity": "1",
			"ConditionQuantityUnit": "PC",
			"ConditionCategory": "",
			"PricingScaleType": "",
			"ConditionRecord": "0000006848",
			"ConditionSequentialNumber": "1",
			"TaxCode": "",
			"ConditionAmount": "15000.00",
			"TransactionCurrency": "EUR",
			"PricingScaleBasis": "",
			"ConditionScaleBasisValue": "0.000000000",
			"ConditionScaleBasisUnit": "",
			"ConditionScaleBasisCurrency": "",
			"ConditionIsManuallyChanged": false
		},
		{
			"SalesInquiry": "10000000",
			"SalesInquiryItem": "10",
			"PricingProcedureStep": "915",
			"PricingProcedureCounter": "1",
			"ConditionApplication": "V",
			"ConditionType": "MWST",
			"PricingDateTime": "2022-09-20",
			"ConditionCalculationType": "A",
			"ConditionBaseValue": "15000.000000000",
			"ConditionRateValue": "16.000000000",
			"ConditionCurrency": "",
			"ConditionQuantity": "0",
			"ConditionQuantityUnit": "",
			"ConditionCategory": "D",
			"PricingScaleType": "",
			"ConditionRecord": "0000006851",
			"ConditionSequentialNumber": "1",
			"TaxCode": "A1",
			"ConditionAmount": "2400.00",
			"TransactionCurrency": "EUR",
			"PricingScaleBasis": "",
			"ConditionScaleBasisValue": "0.000000000",
			"ConditionScaleBasisUnit": "",
			"ConditionScaleBasisCurrency": "",
			"ConditionIsManuallyChanged": false
		},
		{
			"SalesInquiry": "10000000",
			"SalesInquiryItem": "10",
			"PricingProcedureStep": "940",
			"PricingProcedureCounter": "1",
			"ConditionApplication": "V",
			"ConditionType": "VPRS",
			"PricingDateTime": "1998-02-01",
			"ConditionCalculationType": "C",
			"ConditionBaseValue": "15.000000000",
			"ConditionRateValue": "1000.000000000",
			"ConditionCurrency": "EUR",
			"ConditionQuantity": "1",
			"ConditionQuantityUnit": "PC",
			"ConditionCategory": "G",
			"PricingScaleType": "",
			"ConditionRecord": "",
			"ConditionSequentialNumber": "0",
			"TaxCode": "",
			"ConditionAmount": "15000.00",
			"TransactionCurrency": "EUR",
			"PricingScaleBasis": "",
			"ConditionScaleBasisValue": "0.000000000",
			"ConditionScaleBasisUnit": "",
			"ConditionScaleBasisCurrency": "",
			"ConditionIsManuallyChanged": false
		}
	],
	"time": "2022-09-20T16:58:19+09:00"
}
